quickdna/__init__.py
quickdna/.gitignore
quickdna/quickdna.cpython-310-x86_64-linux-gnu.so
quickdna/py.typed
quickdna-0.5.0.dist-info/RECORD
quickdna-0.5.0.dist-info/METADATA
quickdna-0.5.0.dist-info/WHEEL
