Metadata-Version: 2.1
Name: quickdna
Version: 0.5.0
Author: Theia Vogel <theia@vgel.me>
Author-email: Theia Vogel <theia@vgel.me>
